[{"summonerName":"bwuelikebwue","gameId":4921644187},{"summonerName":"bwuelikebwue","gameId":4899891694},{"summonerName":"bwuelikebwue","gameId":4899611316},{"summonerName":"bwuelikebwue","gameId":4897704928},{"summonerName":"bwuelikebwue","gameId":4897560065},{"summonerName":"bwuelikebwue","gameId":4896866286},{"summonerName":"bwuelikebwue","gameId":4895715370},{"summonerName":"bwuelikebwue","gameId":4895597121},{"summonerName":"bwuelikebwue","gameId":4894874301},{"summonerName":"AdiTheGoodGuy","gameId":4990872451},{"summonerName":"Ben Platt","gameId":4998509090},{"summonerName":"felipé énglert","gameId":4924444214},{"summonerName":"scarface xyz","gameId":4994751563}]