[{"summonerName":"FIaresz","gameId":3719544238},{"summonerName":"FIaresz","gameId":3673183412},{"summonerName":"FIaresz","gameId":3669167227},{"summonerName":"FIaresz","gameId":3656229075},{"summonerName":"FIaresz","gameId":3645820977},{"summonerName":"FIaresz","gameId":3645716578},{"summonerName":"FIaresz","gameId":3644518491},{"summonerName":"FIaresz","gameId":3630880253},{"summonerName":"FIaresz","gameId":3626814352},{"summonerName":"Anticípation","gameId":3661154898},{"summonerName":"yeedam2","gameId":3705940142}]