[{"summonerName":"Ventairxyz","gameId":4998963563,"server":"EUW1"},{"summonerName":"Dragane","gameId":4928410876,"server":"EUW1"},{"summonerName":"Ben Platt","gameId":4998605175,"server":"EUW1"},{"summonerName":"Ben Platt","gameId":4995642155,"server":"EUW1"},{"summonerName":"i dodge all","gameId":5000908378,"server":"EUW1"},{"summonerName":"i dodge all","gameId":4999870760,"server":"EUW1"},{"summonerName":"i dodge all","gameId":4999551086,"server":"EUW1"},{"summonerName":"i dodge all","gameId":4998883327,"server":"EUW1"},{"summonerName":"i dodge all","gameId":4998788385,"server":"EUW1"},{"summonerName":"i dodge all","gameId":4998213566,"server":"EUW1"},{"summonerName":"scarface xyz","gameId":4979749247,"server":"EUW1"}]