[{"summonerName":"very artistic1","gameId":5006994597},{"summonerName":"very artistic1","gameId":5006960523},{"summonerName":"very artistic1","gameId":5006291749},{"summonerName":"very artistic1","gameId":5005541817},{"summonerName":"very artistic1","gameId":5003694625},{"summonerName":"very artistic1","gameId":5003007202},{"summonerName":"very artistic1","gameId":4999205448},{"summonerName":"very artistic1","gameId":4998616908},{"summonerName":"Ben Platt","gameId":5000459340},{"summonerName":"kirei smurfer","gameId":4999509863},{"summonerName":"kirei smurfer","gameId":4996981930}]