[{"summonerName":"5tunt","gameId":3709609383,"server":"NA1"},{"summonerName":"Revenge","gameId":3722992826,"server":"NA1"},{"summonerName":"Uma Jan pupil","gameId":3709626034,"server":"NA1"},{"summonerName":"ADCADC123","gameId":3648599191,"server":"NA1"},{"summonerName":"ADCADC123","gameId":3647011289,"server":"NA1"},{"summonerName":"ADCADC123","gameId":3641118723,"server":"NA1"},{"summonerName":"ADCADC123","gameId":3640604613,"server":"NA1"},{"summonerName":"ADCADC123","gameId":3637689542,"server":"NA1"},{"summonerName":"ADCADC123","gameId":3636409347,"server":"NA1"},{"summonerName":"ADCADC123","gameId":3634585921,"server":"NA1"}]